anomalytda_client/__init__.py
anomalytda_client/constants.py
anomalytda_client/files.py
anomalytda_client/internal/__init__.py
anomalytda_client/internal/_anomaly.py
anomalytda_client/internal/_anomaly_v2.py
anomalytda_client/internal/_detection.py
anomalytda_client/internal/_grid_crop.py
anomalytda_client/internal/_logging.py
anomalytda_client/internal/_model.py
anomalytda_client/internal/_transforms.py
anomalytda_client/tools.py
anomalytda_client-0.2.1.dist-info/METADATA
anomalytda_client-0.2.1.dist-info/WHEEL
anomalytda_client-0.2.1.dist-info/RECORD
