Metadata-Version: 2.1
Name: anomalytda-client
Version: 0.2.1
Summary: The AnomalyTDA Client Library
Author: Datarefiner
Author-email: admin@datarefiner.com
Requires-Python: >=3.8,<4.0
Classifier: Programming Language :: Python :: 3
Classifier: Programming Language :: Python :: 3.8
Classifier: Programming Language :: Python :: 3.9
Classifier: Programming Language :: Python :: 3.10
Classifier: Programming Language :: Python :: 3.11
Requires-Dist: matplotlib (>=3.7.5,<4.0.0)
Requires-Dist: numpy (>=1.24.0,<2.0.0)
Requires-Dist: onnxruntime (>=1.19.2,<2.0.0)
Requires-Dist: opencv-python (>=4.6.0,<5.0.0)
Requires-Dist: pillow (>=10.4)
Requires-Dist: scipy (>=1.9.3,<2.0.0)
Requires-Dist: tqdm (>=4.67.0,<5.0.0)
